<?xml version="1.0" encoding="utf-8"?><HelpTOCNode Title="TextOptions Properties" Url="html/Properties_T_xserver_TextOptions.htm"><HelpTOCNode Title="alignment Property " Url="html/P_xserver_TextOptions_alignment.htm" /><HelpTOCNode Title="bgColor Property " Url="html/P_xserver_TextOptions_bgColor.htm" /><HelpTOCNode Title="fillBg Property " Url="html/P_xserver_TextOptions_fillBg.htm" /><HelpTOCNode Title="font Property " Url="html/P_xserver_TextOptions_font.htm" /><HelpTOCNode Title="frameColor Property " Url="html/P_xserver_TextOptions_frameColor.htm" /><HelpTOCNode Title="pixelX Property " Url="html/P_xserver_TextOptions_pixelX.htm" /><HelpTOCNode Title="pixelY Property " Url="html/P_xserver_TextOptions_pixelY.htm" /><HelpTOCNode Title="relX Property " Url="html/P_xserver_TextOptions_relX.htm" /><HelpTOCNode Title="relY Property " Url="html/P_xserver_TextOptions_relY.htm" /><HelpTOCNode Title="showFrame Property " Url="html/P_xserver_TextOptions_showFrame.htm" /><HelpTOCNode Title="textColor Property " Url="html/P_xserver_TextOptions_textColor.htm" /></HelpTOCNode>